github_languages/__init__.py
github_languages/date.py
github_languages-0.1.3.dist-info/LICENSE.md
github_languages-0.1.3.dist-info/METADATA
github_languages-0.1.3.dist-info/WHEEL
github_languages-0.1.3.dist-info/top_level.txt
github_languages-0.1.3.dist-info/RECORD
